[
  {
    "x": 1244,
    "y": 302
  },
  {
    "x": 1159,
    "y": 299
  },
  {
    "x": 1070,
    "y": 293
  },
  {
    "x": 1000,
    "y": 292
  },
  {
    "x": 931,
    "y": 288
  },
  {
    "x": 882,
    "y": 282
  },
  {
    "x": 856,
    "y": 278
  },
  {
    "x": 836,
    "y": 273
  },
  {
    "x": 827,
    "y": 269
  },
  {
    "x": 823,
    "y": 266
  },
  {
    "x": 815,
    "y": 262
  },
  {
    "x": 806,
    "y": 259
  },
  {
    "x": 794,
    "y": 252
  },
  {
    "x": 780,
    "y": 244
  },
  {
    "x": 766,
    "y": 234
  },
  {
    "x": 755,
    "y": 227
  },
  {
    "x": 742,
    "y": 221
  },
  {
    "x": 735,
    "y": 218
  },
  {
    "x": 733,
    "y": 217
  },
  {
    "x": 732,
    "y": 217
  },
  {
    "x": 732,
    "y": 217
  },
  {
    "x": 830,
    "y": 447
  },
  {
    "x": 846,
    "y": 460
  },
  {
    "x": 855,
    "y": 482
  },
  {
    "x": 688,
    "y": 35
  },
  {
    "x": 642,
    "y": 47
  },
  {
    "x": 601,
    "y": 61
  },
  {
    "x": 559,
    "y": 79
  },
  {
    "x": 521,
    "y": 95
  },
  {
    "x": 484,
    "y": 114
  },
  {
    "x": 455,
    "y": 128
  },
  {
    "x": 429,
    "y": 142
  },
  {
    "x": 402,
    "y": 156
  },
  {
    "x": 377,
    "y": 163
  },
  {
    "x": 356,
    "y": 170
  },
  {
    "x": 345,
    "y": 173
  },
  {
    "x": 324,
    "y": 180
  },
  {
    "x": 305,
    "y": 190
  },
  {
    "x": 281,
    "y": 196
  },
  {
    "x": 258,
    "y": 207
  },
  {
    "x": 239,
    "y": 215
  },
  {
    "x": 217,
    "y": 229
  },
  {
    "x": 189,
    "y": 244
  },
  {
    "x": 168,
    "y": 263
  },
  {
    "x": 150,
    "y": 286
  },
  {
    "x": 135,
    "y": 313
  },
  {
    "x": 121,
    "y": 345
  },
  {
    "x": 115,
    "y": 378
  },
  {
    "x": 115,
    "y": 406
  },
  {
    "x": 115,
    "y": 438
  },
  {
    "x": 129,
    "y": 464
  },
  {
    "x": 148,
    "y": 494
  },
  {
    "x": 164,
    "y": 515
  },
  {
    "x": 180,
    "y": 535
  },
  {
    "x": 199,
    "y": 551
  },
  {
    "x": 222,
    "y": 564
  },
  {
    "x": 248,
    "y": 574
  },
  {
    "x": 268,
    "y": 581
  },
  {
    "x": 291,
    "y": 585
  },
  {
    "x": 308,
    "y": 585
  },
  {
    "x": 325,
    "y": 585
  },
  {
    "x": 337,
    "y": 583
  },
  {
    "x": 365,
    "y": 573
  },
  {
    "x": 398,
    "y": 559
  },
  {
    "x": 427,
    "y": 543
  },
  {
    "x": 449,
    "y": 525
  },
  {
    "x": 467,
    "y": 498
  },
  {
    "x": 481,
    "y": 470
  },
  {
    "x": 489,
    "y": 447
  },
  {
    "x": 494,
    "y": 427
  },
  {
    "x": 492,
    "y": 405
  },
  {
    "x": 475,
    "y": 374
  },
  {
    "x": 457,
    "y": 347
  },
  {
    "x": 435,
    "y": 325
  },
  {
    "x": 405,
    "y": 308
  },
  {
    "x": 349,
    "y": 278
  },
  {
    "x": 295,
    "y": 260
  },
  {
    "x": 243,
    "y": 248
  },
  {
    "x": 193,
    "y": 239
  },
  {
    "x": 155,
    "y": 238
  },
  {
    "x": 123,
    "y": 238
  },
  {
    "x": 89,
    "y": 250
  },
  {
    "x": 60,
    "y": 264
  },
  {
    "x": 30,
    "y": 282
  },
  {
    "x": 10,
    "y": 296
  },
  {
    "x": 1,
    "y": 303
  },
  {
    "x": 0,
    "y": 468
  },
  {
    "x": 33,
    "y": 502
  },
  {
    "x": 76,
    "y": 521
  },
  {
    "x": 130,
    "y": 536
  },
  {
    "x": 174,
    "y": 544
  },
  {
    "x": 220,
    "y": 549
  },
  {
    "x": 263,
    "y": 549
  },
  {
    "x": 300,
    "y": 549
  },
  {
    "x": 324,
    "y": 546
  },
  {
    "x": 339,
    "y": 539
  },
  {
    "x": 346,
    "y": 534
  },
  {
    "x": 351,
    "y": 530
  },
  {
    "x": 358,
    "y": 521
  },
  {
    "x": 363,
    "y": 513
  },
  {
    "x": 366,
    "y": 509
  },
  {
    "x": 369,
    "y": 502
  },
  {
    "x": 372,
    "y": 498
  },
  {
    "x": 379,
    "y": 492
  },
  {
    "x": 390,
    "y": 480
  },
  {
    "x": 407,
    "y": 457
  },
  {
    "x": 425,
    "y": 437
  },
  {
    "x": 438,
    "y": 410
  },
  {
    "x": 450,
    "y": 386
  },
  {
    "x": 456,
    "y": 362
  },
  {
    "x": 456,
    "y": 342
  },
  {
    "x": 445,
    "y": 316
  },
  {
    "x": 417,
    "y": 290
  },
  {
    "x": 361,
    "y": 263
  },
  {
    "x": 286,
    "y": 239
  },
  {
    "x": 237,
    "y": 235
  },
  {
    "x": 203,
    "y": 238
  },
  {
    "x": 183,
    "y": 254
  },
  {
    "x": 171,
    "y": 284
  },
  {
    "x": 162,
    "y": 337
  },
  {
    "x": 162,
    "y": 391
  },
  {
    "x": 175,
    "y": 452
  },
  {
    "x": 205,
    "y": 516
  },
  {
    "x": 254,
    "y": 582
  },
  {
    "x": 310,
    "y": 622
  },
  {
    "x": 371,
    "y": 649
  },
  {
    "x": 445,
    "y": 669
  },
  {
    "x": 499,
    "y": 669
  },
  {
    "x": 548,
    "y": 650
  },
  {
    "x": 601,
    "y": 615
  },
  {
    "x": 641,
    "y": 567
  },
  {
    "x": 660,
    "y": 513
  },
  {
    "x": 664,
    "y": 455
  },
  {
    "x": 655,
    "y": 406
  },
  {
    "x": 625,
    "y": 356
  },
  {
    "x": 574,
    "y": 306
  },
  {
    "x": 525,
    "y": 278
  },
  {
    "x": 487,
    "y": 262
  },
  {
    "x": 453,
    "y": 256
  },
  {
    "x": 426,
    "y": 256
  },
  {
    "x": 395,
    "y": 256
  },
  {
    "x": 361,
    "y": 264
  },
  {
    "x": 328,
    "y": 277
  },
  {
    "x": 300,
    "y": 296
  },
  {
    "x": 273,
    "y": 327
  },
  {
    "x": 257,
    "y": 362
  },
  {
    "x": 249,
    "y": 402
  },
  {
    "x": 249,
    "y": 443
  },
  {
    "x": 268,
    "y": 477
  },
  {
    "x": 291,
    "y": 502
  },
  {
    "x": 334,
    "y": 519
  },
  {
    "x": 390,
    "y": 523
  },
  {
    "x": 464,
    "y": 518
  },
  {
    "x": 567,
    "y": 491
  },
  {
    "x": 634,
    "y": 450
  },
  {
    "x": 683,
    "y": 410
  },
  {
    "x": 693,
    "y": 391
  },
  {
    "x": 684,
    "y": 255
  },
  {
    "x": 661,
    "y": 220
  },
  {
    "x": 625,
    "y": 188
  },
  {
    "x": 583,
    "y": 167
  },
  {
    "x": 534,
    "y": 150
  },
  {
    "x": 494,
    "y": 141
  },
  {
    "x": 466,
    "y": 139
  },
  {
    "x": 440,
    "y": 139
  },
  {
    "x": 412,
    "y": 154
  },
  {
    "x": 385,
    "y": 169
  },
  {
    "x": 362,
    "y": 190
  },
  {
    "x": 340,
    "y": 216
  },
  {
    "x": 330,
    "y": 237
  },
  {
    "x": 328,
    "y": 252
  },
  {
    "x": 333,
    "y": 265
  },
  {
    "x": 355,
    "y": 275
  },
  {
    "x": 385,
    "y": 284
  },
  {
    "x": 426,
    "y": 287
  },
  {
    "x": 476,
    "y": 287
  },
  {
    "x": 518,
    "y": 287
  },
  {
    "x": 554,
    "y": 287
  },
  {
    "x": 580,
    "y": 287
  },
  {
    "x": 595,
    "y": 287
  },
  {
    "x": 612,
    "y": 283
  },
  {
    "x": 621,
    "y": 281
  },
  {
    "x": 629,
    "y": 280
  },
  {
    "x": 639,
    "y": 276
  },
  {
    "x": 654,
    "y": 276
  },
  {
    "x": 679,
    "y": 276
  },
  {
    "x": 693,
    "y": 278
  },
  {
    "x": 692,
    "y": 180
  },
  {
    "x": 664,
    "y": 92
  },
  {
    "x": 655,
    "y": 68
  },
  {
    "x": 654,
    "y": 55
  },
  {
    "x": 654,
    "y": 47
  },
  {
    "x": 654,
    "y": 42
  },
  {
    "x": 654,
    "y": 40
  },
  {
    "x": 655,
    "y": 39
  },
  {
    "x": 670,
    "y": 44
  },
  {
    "x": 679,
    "y": 49
  },
  {
    "x": 684,
    "y": 53
  },
  {
    "x": 687,
    "y": 53
  },
  {
    "x": 689,
    "y": 55
  },
  {
    "x": 690,
    "y": 55
  },
  {
    "x": 691,
    "y": 54
  },
  {
    "x": 693,
    "y": 53
  }
]
